thisday/__init__.py
thisday/__main__.py
thisday/thisday.py
thisday-1.0.dist-info/LICENSE
thisday-1.0.dist-info/METADATA
thisday-1.0.dist-info/WHEEL
thisday-1.0.dist-info/entry_points.txt
thisday-1.0.dist-info/top_level.txt
thisday-1.0.dist-info/RECORD
