Metadata-Version: 2.1
Name: thisday
Version: 1.0
Summary: A package to get the data from onthisday.com.
Author-email: Danilo Montes <dem9855@nyu.edu>, Anvi Agarwal <aa7140@nyu.edu>, Leo Xu <gx324@nyu.edu>, Otis <zl2883@nyu.edu>
License: GNU GENERAL PUBLIC LICENSE
Project-URL: Homepage, https://github.com/software-students-fall2022/python-package-exercise-project-3-team-2
Project-URL: Repository, https://github.com/software-students-fall2022/python-package-exercise-project-3-team-2.git
Project-URL: Bug Tracker, https://github.com/software-students-fall2022/python-package-exercise-project-3-team-2/issues
Keywords: python,package,build,tutorial
Classifier: Programming Language :: Python :: 3
Classifier: License :: OSI Approved :: GNU General Public License v3 (GPLv3)
Classifier: Operating System :: OS Independent
Requires-Python: >=3
License-File: LICENSE
Provides-Extra: dev
Requires-Dist: pytest ; extra == 'dev'
